README.md
setup.cfg
setup.py
globeos/__init__.py
globeos.egg-info/PKG-INFO
globeos.egg-info/SOURCES.txt
globeos.egg-info/dependency_links.txt
globeos.egg-info/requires.txt
globeos.egg-info/top_level.txt
globeos/utils/__init__.py
globeos/utils/dynamicsceneloader.py
globeos/utils/timing.py