Metadata-Version: 1.1
Name: globeos
Version: 0.1.0
Summary: Package to display data on globe
Home-page: https://github.com/JMDriver/GlobeOS
Author: James Driver
Author-email: jad44@aber.ac.uk
License: UNKNOWN
Download-URL: https://github.com/jmdriver/globeos/archive/0.1.0.tar.gz
Platform: UNKNOWN
